lander/__init__.py
lander/config.py
lander/exceptions.py
lander/lander.py
lander/ltdclient.py
lander/main.py
lander/renderer.py
lander/assets/app.bundle.js
lander/assets/app.css
lander/assets/lsst_underline_logo.svg
lander/lsstprojectmeta/__init__.py
lander/lsstprojectmeta/jsonld.py
lander/lsstprojectmeta/ltd.py
lander/lsstprojectmeta/cli/__init__.py
lander/lsstprojectmeta/cli/ingestdocs.py
lander/lsstprojectmeta/data/githubv4/README.rst
lander/lsstprojectmeta/data/githubv4/technote_repo.graphql
lander/lsstprojectmeta/git/__init__.py
lander/lsstprojectmeta/git/timestamp.py
lander/lsstprojectmeta/github/__init__.py
lander/lsstprojectmeta/github/auth.py
lander/lsstprojectmeta/github/graphql.py
lander/lsstprojectmeta/github/urls.py
lander/lsstprojectmeta/lsstdocument/__init__.py
lander/lsstprojectmeta/lsstdocument/handles.py
lander/lsstprojectmeta/lsstdocument/lander.py
lander/lsstprojectmeta/lsstdocument/sphinxtechnotes.py
lander/lsstprojectmeta/pandoc/__init__.py
lander/lsstprojectmeta/pandoc/convert.py
lander/lsstprojectmeta/pandoc/filters/__init__.py
lander/lsstprojectmeta/pandoc/filters/deparagraph.py
lander/lsstprojectmeta/tex/__init__.py
lander/lsstprojectmeta/tex/citelink.py
lander/lsstprojectmeta/tex/commandparser.py
lander/lsstprojectmeta/tex/lsstbib.py
lander/lsstprojectmeta/tex/lsstdoc.py
lander/lsstprojectmeta/tex/lsstmacros.py
lander/lsstprojectmeta/tex/normalizer.py
lander/lsstprojectmeta/tex/scraper.py
lander/metadata/__init__.py
lander/metadata/base.py
lander/metadata/highwire.py
lander/metadata/opengraph.py
lander/templates/_footer.jinja
lander/templates/_info-panel.jinja
lander/templates/_typekit_loader.jinja
lander/templates/base.jinja
lander/templates/homepage.jinja
lander/templates/icons.svg
lander-1.1.0.dist-info/licenses/LICENSE
lander-1.1.0.dist-info/METADATA
lander-1.1.0.dist-info/WHEEL
lander-1.1.0.dist-info/entry_points.txt
lander-1.1.0.dist-info/top_level.txt
lander-1.1.0.dist-info/RECORD
