Metadata-Version: 2.4
Name: lander
Version: 1.1.0
Summary: HTML landing page generator for LSST PDF documentation deployed from Git to LSST the Docs.
Home-page: https://github.com/lsst-sqre/lander
Author: Association of Universities for Research in Astronomy, Inc. (AURA)
Author-email: sqre-admin@lists.lsst.org
Project-URL: Change log, https://github.com/lsst-sqre/lander/blob/master/CHANGELOG.rst
Project-URL: Source code, https://github.com/lsst-sqre/lander
Project-URL: Issue tracker, https://github.com/lsst-sqre/lander/issues
Keywords: lsst
Classifier: Development Status :: 4 - Beta
Classifier: License :: OSI Approved :: MIT License
Classifier: Programming Language :: Python
Classifier: Programming Language :: Python :: 3
Classifier: Programming Language :: Python :: 3.8
Classifier: Programming Language :: Python :: 3.9
Classifier: Programming Language :: Python :: 3.10
Classifier: Programming Language :: Python :: 3.11
Classifier: Programming Language :: Python :: 3.12
Classifier: Programming Language :: Python :: 3.13
Classifier: Intended Audience :: Developers
Classifier: Natural Language :: English
Classifier: Operating System :: POSIX
Requires-Python: >=3.8
License-File: LICENSE
Requires-Dist: importlib_metadata; python_version < "3.8"
Requires-Dist: python-dateutil>=2.6.0
Requires-Dist: Jinja2>=2.10.1
Requires-Dist: MarkupSafe
Requires-Dist: structlog
Requires-Dist: ltd-conveyor
Requires-Dist: requests
Requires-Dist: pydantic<2.0.0
Requires-Dist: click
Requires-Dist: pypandoc
Requires-Dist: panflute
Requires-Dist: pybtex
Requires-Dist: pytz
Requires-Dist: aiohttp
Requires-Dist: GitPython
Requires-Dist: setuptools<81
Provides-Extra: dev
Requires-Dist: pytest; extra == "dev"
Requires-Dist: pytest-cov; extra == "dev"
Requires-Dist: pytest-flake8; extra == "dev"
Requires-Dist: pre-commit; extra == "dev"
Requires-Dist: types-setuptools; extra == "dev"
Requires-Dist: types-requests; extra == "dev"
Dynamic: license-file
